cps3/__init__.py
cps3/cpsish.py
cps3/main.py
fassst/__init__.py
fassst/cpsish.py
fassst/main.py
cps3-1.0.0.dist-info/LICENSE
cps3-1.0.0.dist-info/METADATA
cps3-1.0.0.dist-info/WHEEL
cps3-1.0.0.dist-info/entry_points.txt
cps3-1.0.0.dist-info/top_level.txt
cps3-1.0.0.dist-info/RECORD
